cajun_name_generator/__init__.py
cajun_name_generator/cajun_name_generator.py
cajun_name_generator/cajunnamelist.py
cajun_name_generator/example.py
cajun_name_generator-0.2.2.dist-info/LICENSE
cajun_name_generator-0.2.2.dist-info/METADATA
cajun_name_generator-0.2.2.dist-info/WHEEL
cajun_name_generator-0.2.2.dist-info/top_level.txt
cajun_name_generator-0.2.2.dist-info/RECORD
