Metadata-Version: 2.1
Name: cajun-name-generator
Version: 0.2.2
Summary: Package to generate random Cajun first and last names.
Home-page: https://github.com/adammelancon/cajun_name_generator
Author: Adam Melancon
Author-email: adammelancon@gmail.com
License: MIT license
Keywords: cajun_name_generator
Platform: UNKNOWN
Classifier: License :: OSI Approved :: MIT License
Classifier: Natural Language :: English
Classifier: Programming Language :: Python :: 3
Classifier: Programming Language :: Python :: 3.6
Classifier: Programming Language :: Python :: 3.7
Classifier: Programming Language :: Python :: 3.8
Requires-Python: >=3.6
License-File: LICENSE
